tic_tac_toe_game/AI/__init__.py
tic_tac_toe_game/AI/mcts.py
tic_tac_toe_game/AI/naive.py
tic_tac_toe_game/AI/negamax.py
tic_tac_toe_game/__init__.py
tic_tac_toe_game/__main__.py
tic_tac_toe_game/engine.py
tic_tac_toe_game/errors.py
tic_tac_toe_game/py.typed
tic_tac_toe_game/state.py
tic_tac_toe_game/typing.py
tic_tac_toe_game-0.2.0.dist-info/entry_points.txt
tic_tac_toe_game-0.2.0.dist-info/METADATA
tic_tac_toe_game-0.2.0.dist-info/LICENSE
tic_tac_toe_game-0.2.0.dist-info/WHEEL
tic_tac_toe_game-0.2.0.dist-info/RECORD
