Metadata-Version: 2.1
Name: tic-tac-toe-game
Version: 0.2.0
Summary: Tic Tac Toe Game
Home-page: https://github.com/alexistli/tic-tac-toe-game
License: MIT
Author: Alexis Torelli
Author-email: alexis.torelli.treanton@gmail.com
Requires-Python: >=3.8,<4.0
Classifier: Development Status :: 4 - Beta
Classifier: License :: OSI Approved :: MIT License
Classifier: Programming Language :: Python :: 3
Classifier: Programming Language :: Python :: 3.8
Classifier: Programming Language :: Python :: 3.9
Classifier: Programming Language :: Python :: 3.10
Classifier: Programming Language :: Python :: 3.11
Requires-Dist: Flask (>=2.2.2,<3.0.0)
Requires-Dist: Flask-Assets (>=2.0,<3.0)
Requires-Dist: Flask-Migrate (>=4.0.0,<5.0.0)
Requires-Dist: Flask-SQLAlchemy (>=3.0.2,<4.0.0)
Requires-Dist: Flask-Session (>=0.4.0,<0.5.0)
Requires-Dist: Flask-SocketIO (>=5.3.2,<6.0.0)
Requires-Dist: Flask-WTF (>=1.0.1,<2.0.0)
Requires-Dist: click (>=8.1.3,<9.0.0)
Requires-Dist: easyAI (>=2.0.12,<3.0.0)
Requires-Dist: eventlet (>=0.33.2,<0.34.0)
Requires-Dist: gunicorn (>=20.1.0,<21.0.0)
Requires-Dist: mctspy (>=0.1.1,<0.2.0)
Requires-Dist: python-dotenv (>=0.21.0,<0.22.0)
Requires-Dist: redis (>=4.4.0,<5.0.0)
Requires-Dist: rich (>=12.6.0,<13.0.0)
Requires-Dist: structlog (>=22.3.0,<23.0.0)
Project-URL: Changelog, https://github.com/alexistli/tic-tac-toe-game/releases
Project-URL: Documentation, https://tic-tac-toe-game.readthedocs.io
Project-URL: Repository, https://github.com/alexistli/tic-tac-toe-game
